{
    "name": "产业链数字生态资源子系统评价",
    "children": [
        {
            "name": "活力",
            "children": [
                {
                    "name": "生产力",
                    "children": [
                        { "name": "产出数量" },
                        { "name": "创新产量" }
                    ]
                },
                {
                    "name": "流通力",
                    "children": [
                        { "name": "数据覆盖率" },
                        { "name": "流动效率" }
                    ]
                },
                {
                    "name": "代谢力",
                    "children": [
                        { "name": "流程整合能力" },
                        { "name": "更新淘汰能力" }
                    ]
                }
            ]
        },
        {
            "name": "组织力",
            "children": [
                {
                    "name": "结构性",
                    "children": [
                        { "name": "构件层级深度" }
                    ]
                },
                {
                    "name": "多样性",
                    "children": [
                        { "name": "数字资源多样性" }
                    ]
                },
                {
                    "name": "互动性",
                    "children": [
                        { "name": "算法协作程度" },
                        { "name": "数字资源竞争程度" }
                    ]
                }
            ]
        },
        {
            "name": "服务能力",
            "children": [
                {
                    "name": "供给服务",
                    "children": [
                        { "name": "平均接口响应时间" }
                    ]
                }
            ]
        }
    ]
}